mms_python_adapter/__init__.py
mms_python_adapter/mms_python_adapter.py
mms_python_adapter-1.2.5.dist-info/LICENSE
mms_python_adapter-1.2.5.dist-info/METADATA
mms_python_adapter-1.2.5.dist-info/WHEEL
mms_python_adapter-1.2.5.dist-info/top_level.txt
mms_python_adapter-1.2.5.dist-info/RECORD
