Metadata-Version: 2.1
Name: mms-python-adapter
Version: 1.2.5
Summary: MMS Communication
Home-page: https://github.com/Open-MBEE/MMS-Python-Adapter
Author: Tanner J Rosenberg, Lenard Halim
Author-email: Tanner.J.Rosenberg@jpl.nasa.gov, lenard.j.halim@jpl.nasa.gov
License: Apache 2.0
Platform: UNKNOWN
Classifier: Programming Language :: Python :: 3
Requires-Dist: mms-python-client (<4)
